resen/DockerHelper.py
resen/Resen.py
resen/__init__.py
resen/resencmd.py
resen-2021.1.0.dist-info/LICENSE
resen-2021.1.0.dist-info/METADATA
resen-2021.1.0.dist-info/WHEEL
resen-2021.1.0.dist-info/entry_points.txt
resen-2021.1.0.dist-info/top_level.txt
resen-2021.1.0.dist-info/RECORD
