Metadata-Version: 2.1
Name: resen
Version: 2021.1.0
Summary: A python package for watching, copying, and transporting files around.
Home-page: https://ingeo.datatransport.org/home/
Author: NSF Integrated Geoscience Observatory
Author-email: ingeo-team@ingeo.datatransport.org
License: GPLv3
Platform: UNKNOWN
Classifier: Development Status :: 3 - Alpha
Classifier: Intended Audience :: Developers
Classifier: Topic :: Software Development
Classifier: License :: OSI Approved :: GNU General Public License (GPL)
Classifier: Programming Language :: Python :: 3.6
License-File: LICENSE
Requires-Dist: docker (<3.8.0)
